run_causal/__init__.py
run_causal/app_launcher.py
run_causal/causal_forecast.py
run_causal-1.0.3.dist-info/METADATA
run_causal-1.0.3.dist-info/WHEEL
run_causal-1.0.3.dist-info/entry_points.txt
run_causal-1.0.3.dist-info/top_level.txt
run_causal-1.0.3.dist-info/RECORD
