Metadata-Version: 2.2
Name: run_causal
Version: 1.0.3
Summary: Get the causal forecast analysis
Home-page: https://github.com/A284viral/run_causal
Author: Aviral Srivastava
Author-email: aviralsrivastava284@gmail.com
Classifier: Programming Language :: Python :: 3
Classifier: License :: OSI Approved :: MIT License
Classifier: Operating System :: OS Independent
Requires-Python: >=3.6
Requires-Dist: catboost==1.2.8
Requires-Dist: streamlit==1.45.1
Requires-Dist: numpy==2.2.6
Requires-Dist: pandas==2.2.3
Requires-Dist: matplotlib==3.10.3
Requires-Dist: scikit-learn==1.6.1
Requires-Dist: shap==0.47.2
Requires-Dist: scipy==1.15.3
Requires-Dist: statsmodels==0.14.4
Requires-Dist: xgboost==3.0.1
Dynamic: author
Dynamic: author-email
Dynamic: classifier
Dynamic: description-content-type
Dynamic: home-page
Dynamic: requires-dist
Dynamic: requires-python
Dynamic: summary
